[
  {
    "weight": 83.2,
    "weightedAt": "morning",
    "date": "2025-06-28T07:30:00Z"
  },
  {
    "weight": 83.1,
    "weightedAt": "morning",
    "date": "2025-06-29T07:30:00Z"
  },
  {
    "weight": 82.9,
    "weightedAt": "morning",
    "date": "2025-06-30T07:30:00Z"
  },
  {
    "weight": 83.0,
    "weightedAt": "morning",
    "date": "2025-07-01T07:30:00Z"
  },
  {
    "weight": 82.8,
    "weightedAt": "morning",
    "date": "2025-07-02T07:30:00Z"
  },
  {
    "weight": 82.6,
    "weightedAt": "morning",
    "date": "2025-07-03T07:30:00Z"
  },
  {
    "weight": 82.4,
    "weightedAt": "morning",
    "date": "2025-07-04T07:30:00Z"
  },
  {
    "weight": 82.7,
    "weightedAt": "morning",
    "date": "2025-07-05T07:30:00Z"
  },
  {
    "weight": 82.5,
    "weightedAt": "morning",
    "date": "2025-07-06T07:30:00Z"
  },
  {
    "weight": 82.3,
    "weightedAt": "morning",
    "date": "2025-07-07T07:30:00Z"
  },
  {
    "weight": 82.1,
    "weightedAt": "morning",
    "date": "2025-07-08T07:30:00Z"
  },
  {
    "weight": 82.0,
    "weightedAt": "morning",
    "date": "2025-07-09T07:30:00Z"
  },
  {
    "weight": 81.9,
    "weightedAt": "morning",
    "date": "2025-07-10T07:30:00Z"
  },
  {
    "weight": 82.1,
    "weightedAt": "morning",
    "date": "2025-07-11T07:30:00Z"
  },
  {
    "weight": 82.0,
    "weightedAt": "morning",
    "date": "2025-07-12T07:30:00Z"
  },
  {
    "weight": 81.8,
    "weightedAt": "morning",
    "date": "2025-07-13T07:30:00Z"
  },
  {
    "weight": 81.7,
    "weightedAt": "morning",
    "date": "2025-07-14T07:30:00Z"
  },
  {
    "weight": 81.5,
    "weightedAt": "morning",
    "date": "2025-07-15T07:30:00Z"
  },
  {
    "weight": 81.3,
    "weightedAt": "morning",
    "date": "2025-07-16T07:30:00Z"
  },
  {
    "weight": 81.1,
    "weightedAt": "morning",
    "date": "2025-07-17T07:30:00Z"
  },
  {
    "weight": 81.0,
    "weightedAt": "morning",
    "date": "2025-07-18T07:30:00Z"
  },
  {
    "weight": 80.8,
    "weightedAt": "morning",
    "date": "2025-07-19T07:30:00Z"
  },
  {
    "weight": 80.7,
    "weightedAt": "morning",
    "date": "2025-07-20T07:30:00Z"
  },
  {
    "weight": 80.6,
    "weightedAt": "morning",
    "date": "2025-07-21T07:30:00Z"
  },
  {
    "weight": 80.4,
    "weightedAt": "morning",
    "date": "2025-07-22T07:30:00Z"
  },
  {
    "weight": 80.3,
    "weightedAt": "morning",
    "date": "2025-07-23T07:30:00Z"
  },
  {
    "weight": 80.2,
    "weightedAt": "morning",
    "date": "2025-07-24T07:30:00Z"
  },
  {
    "weight": 80.0,
    "weightedAt": "morning",
    "date": "2025-07-25T07:30:00Z"
  },
  {
    "weight": 79.9,
    "weightedAt": "morning",
    "date": "2025-07-26T07:30:00Z"
  },
  {
    "weight": 79.8,
    "weightedAt": "morning",
    "date": "2025-07-27T07:30:00Z"
  }
]
